china_region_data/__init__.py
china_region_data/data.json
china_region_data/datastructures.py
china_region_data/exceptions.py
china_region_data/utils.py
china_region_data-2020.10.dist-info/LICENSE
china_region_data-2020.10.dist-info/WHEEL
china_region_data-2020.10.dist-info/METADATA
china_region_data-2020.10.dist-info/RECORD
