Metadata-Version: 2.1
Name: china-region-data
Version: 2020.10
Summary: 中国行政区域数据
Home-page: https://github.com/abersheeran/china-region-data
License: MIT
Author: abersheeran
Author-email: me@abersheeran.com
Requires-Python: >=3.6,<4.0
Classifier: License :: OSI Approved :: MIT License
Classifier: Programming Language :: Python :: 3
Classifier: Programming Language :: Python :: 3.6
Classifier: Programming Language :: Python :: 3.7
Classifier: Programming Language :: Python :: 3.8
Classifier: Programming Language :: Python :: 3.9
Project-URL: Documentation, https://github.com/abersheeran/china-region-data
Project-URL: Repository, https://github.com/abersheeran/china-region-data
